pytorch_modules/__init__.py
pytorch_modules/__version__.py
pytorch_modules/augments/__init__.py
pytorch_modules/augments/augments.py
pytorch_modules/augments/utils.py
pytorch_modules/backbones/__init__.py
pytorch_modules/backbones/basic.py
pytorch_modules/backbones/efficient.py
pytorch_modules/backbones/efficientnet.py
pytorch_modules/backbones/mini.py
pytorch_modules/backbones/resnet.py
pytorch_modules/datasets/__init__.py
pytorch_modules/datasets/basic.py
pytorch_modules/datasets/classification_dataset.py
pytorch_modules/datasets/detection_dataset.py
pytorch_modules/datasets/lmdb_cache.py
pytorch_modules/datasets/segmentation_dataset.py
pytorch_modules/nn/__init__.py
pytorch_modules/nn/activation.py
pytorch_modules/nn/ada_group_norm.py
pytorch_modules/nn/aspp.py
pytorch_modules/nn/basic.py
pytorch_modules/nn/bifpn.py
pytorch_modules/nn/drop_connect.py
pytorch_modules/nn/empty_layer.py
pytorch_modules/nn/focal.py
pytorch_modules/nn/fpn.py
pytorch_modules/nn/mb_block.py
pytorch_modules/nn/res_block.py
pytorch_modules/nn/se_layer.py
pytorch_modules/nn/spp.py
pytorch_modules/nn/utils.py
pytorch_modules/nn/weight_standard_conv.py
pytorch_modules/optims/__init__.py
pytorch_modules/optims/adabound.py
pytorch_modules/optims/ranger.py
pytorch_modules/utils/__init__.py
pytorch_modules/utils/checkpoint.py
pytorch_modules/utils/fetcher.py
pytorch_modules/utils/freeze.py
pytorch_modules/utils/fuse.py
pytorch_modules/utils/init.py
pytorch_modules/utils/macro.py
pytorch_modules/utils/trainer.py
pytorch_modules-0.3.5.dist-info/DESCRIPTION.rst
pytorch_modules-0.3.5.dist-info/METADATA
pytorch_modules-0.3.5.dist-info/RECORD
pytorch_modules-0.3.5.dist-info/WHEEL
pytorch_modules-0.3.5.dist-info/metadata.json
pytorch_modules-0.3.5.dist-info/top_level.txt
