Metadata-Version: 2.0
Name: pytorch-modules
Version: 0.3.5
Summary: A neural network toolkit.
Home-page: https://github.com/woodsgao/pytorch_modules
Author: woodsgao
Author-email: woodsgao@outlook.com
License: MIT
Platform: UNKNOWN
Classifier: License :: OSI Approved :: GNU General Public License v3 (GPLv3)
Classifier: Programming Language :: Python
Classifier: Programming Language :: Python :: 3
Classifier: Programming Language :: Python :: 3.5
Classifier: Programming Language :: Python :: 3.6
Classifier: Programming Language :: Python :: 3.7
Classifier: Programming Language :: Python :: Implementation :: CPython
Classifier: Programming Language :: Python :: Implementation :: PyPy
Requires-Python: >=3.5.2
Requires-Dist: lmdb (>=0.98)
Requires-Dist: numpy (>=1.11)
Requires-Dist: opencv-python (>=3.3)
Requires-Dist: torch (>=1.3)
Requires-Dist: tqdm
